[
  {
    "Order Date":"2026-07-18",
    "Day":"Saturday.",
    "Order ID":"B3494",
    "Brand Name":"All Day Drinks",
    "Delivery Distance":5.9,
    "Order Hour":16,
    "Prep Time":44,
    "Delivery Time":13,
    "E2E":57,
    "Delivery Channel":"Ando Fleet"
  },
  {
    "Order Date":"2026-07-18",
    "Day":"Saturday.",
    "Order ID":"227648",
    "Brand Name":"Burger King",
    "Delivery Distance":5.3,
    "Order Hour":14,
    "Prep Time":41,
    "Delivery Time":29,
    "E2E":70,
    "Delivery Channel":"Uber Direct"
  },
  {
    "Order Date":"2026-07-18",
    "Day":"Saturday.",
    "Order ID":"F49F9",
    "Brand Name":"Chicago The Pizza Place",
    "Delivery Distance":4.7,
    "Order Hour":20,
    "Prep Time":22,
    "Delivery Time":18,
    "E2E":40,
    "Delivery Channel":"Uber Direct"
  },
  {
    "Order Date":"2026-07-18",
    "Day":"Saturday.",
    "Order ID":"86551",
    "Brand Name":"Chicago The Pizza Place",
    "Delivery Distance":2.8,
    "Order Hour":19,
    "Prep Time":25,
    "Delivery Time":26,
    "E2E":51,
    "Delivery Channel":"Uber Direct"
  },
  {
    "Order Date":"2026-07-18",
    "Day":"Saturday.",
    "Order ID":"BDFCA",
    "Brand Name":"Chicago The Pizza Place",
    "Delivery Distance":3.3,
    "Order Hour":13,
    "Prep Time":18,
    "Delivery Time":22,
    "E2E":40,
    "Delivery Channel":"Uber Direct"
  },
  {
    "Order Date":"2026-07-18",
    "Day":"Saturday.",
    "Order ID":"ABB1F",
    "Brand Name":"Chicago The Pizza Place",
    "Delivery Distance":6.0,
    "Order Hour":13,
    "Prep Time":22,
    "Delivery Time":31,
    "E2E":53,
    "Delivery Channel":"Uber Direct"
  },
  {
    "Order Date":"2026-07-18",
    "Day":"Saturday.",
    "Order ID":"474A2",
    "Brand Name":"Elkababgy",
    "Delivery Distance":9.9,
    "Order Hour":19,
    "Prep Time":50,
    "Delivery Time":34,
    "E2E":84,
    "Delivery Channel":"Uber Direct"
  },
  {
    "Order Date":"2026-07-18",
    "Day":"Saturday.",
    "Order ID":"F2520",
    "Brand Name":"Elkababgy",
    "Delivery Distance":2.9,
    "Order Hour":15,
    "Prep Time":27,
    "Delivery Time":27,
    "E2E":54,
    "Delivery Channel":"Uber Direct"
  },
  {
    "Order Date":"2026-07-18",
    "Day":"Saturday.",
    "Order ID":"D8E80",
    "Brand Name":"Elkababgy",
    "Delivery Distance":6.5,
    "Order Hour":14,
    "Prep Time":29,
    "Delivery Time":20,
    "E2E":49,
    "Delivery Channel":"Uber Direct"
  },
  {
    "Order Date":"2026-07-18",
    "Day":"Saturday.",
    "Order ID":"40F21",
    "Brand Name":"German Point",
    "Delivery Distance":8.1,
    "Order Hour":15,
    "Prep Time":27,
    "Delivery Time":30,
    "E2E":57,
    "Delivery Channel":"Uber Direct"
  },
  {
    "Order Date":"2026-07-18",
    "Day":"Saturday.",
    "Order ID":"978C7",
    "Brand Name":"Ichiban Sushi, B Arcade Mall",
    "Delivery Distance":1.3,
    "Order Hour":20,
    "Prep Time":18,
    "Delivery Time":4,
    "E2E":22,
    "Delivery Channel":"Ando Fleet"
  },
  {
    "Order Date":"2026-07-18",
    "Day":"Saturday.",
    "Order ID":"74AB0",
    "Brand Name":"KAI The Sushi Bar, B Arcade Mall",
    "Delivery Distance":10.6,
    "Order Hour":19,
    "Prep Time":66,
    "Delivery Time":31,
    "E2E":97,
    "Delivery Channel":"Uber Direct"
  },
  {
    "Order Date":"2026-07-18",
    "Day":"Saturday.",
    "Order ID":"101717264504",
    "Brand Name":"KAI The Sushi Bar, B Arcade Mall",
    "Delivery Distance":0.8,
    "Order Hour":20,
    "Prep Time":33,
    "Delivery Time":4,
    "E2E":37,
    "Delivery Channel":"Ando Fleet"
  },
  {
    "Order Date":"2026-07-18",
    "Day":"Saturday.",
    "Order ID":"0CA11",
    "Brand Name":"KAI The Sushi Bar, B Arcade Mall",
    "Delivery Distance":3.7,
    "Order Hour":20,
    "Prep Time":17,
    "Delivery Time":25,
    "E2E":42,
    "Delivery Channel":"Ando Fleet"
  },
  {
    "Order Date":"2026-07-18",
    "Day":"Saturday.",
    "Order ID":"101717204987",
    "Brand Name":"KAI The Sushi Bar, B Arcade Mall",
    "Delivery Distance":1.1,
    "Order Hour":20,
    "Prep Time":17,
    "Delivery Time":1,
    "E2E":18,
    "Delivery Channel":"Ando Fleet"
  },
  {
    "Order Date":"2026-07-18",
    "Day":"Saturday.",
    "Order ID":"6313B",
    "Brand Name":"KAI The Sushi Bar, B Arcade Mall",
    "Delivery Distance":5.3,
    "Order Hour":19,
    "Prep Time":47,
    "Delivery Time":4,
    "E2E":51,
    "Delivery Channel":"Ando Fleet"
  },
  {
    "Order Date":"2026-07-18",
    "Day":"Saturday.",
    "Order ID":"1010717176132",
    "Brand Name":"KAI The Sushi Bar, B Arcade Mall",
    "Delivery Distance":2.3,
    "Order Hour":19,
    "Prep Time":37,
    "Delivery Time":11,
    "E2E":48,
    "Delivery Channel":"Ando Fleet"
  },
  {
    "Order Date":"2026-07-18",
    "Day":"Saturday.",
    "Order ID":"095D6",
    "Brand Name":"KAI The Sushi Bar, B Arcade Mall",
    "Delivery Distance":4.9,
    "Order Hour":19,
    "Prep Time":38,
    "Delivery Time":19,
    "E2E":57,
    "Delivery Channel":"Ando Fleet"
  },
  {
    "Order Date":"2026-07-18",
    "Day":"Saturday.",
    "Order ID":"D8390",
    "Brand Name":"KAI The Sushi Bar, B Arcade Mall",
    "Delivery Distance":10.1,
    "Order Hour":18,
    "Prep Time":31,
    "Delivery Time":24,
    "E2E":55,
    "Delivery Channel":"Ando Fleet"
  },
  {
    "Order Date":"2026-07-18",
    "Day":"Saturday.",
    "Order ID":"101717099543",
    "Brand Name":"KAI The Sushi Bar, B Arcade Mall",
    "Delivery Distance":2.6,
    "Order Hour":18,
    "Prep Time":15,
    "Delivery Time":27,
    "E2E":42,
    "Delivery Channel":"Ando Fleet"
  },
  {
    "Order Date":"2026-07-18",
    "Day":"Saturday.",
    "Order ID":"101717099814",
    "Brand Name":"KAI The Sushi Bar, B Arcade Mall",
    "Delivery Distance":2.3,
    "Order Hour":18,
    "Prep Time":33,
    "Delivery Time":18,
    "E2E":51,
    "Delivery Channel":"Ando Fleet"
  },
  {
    "Order Date":"2026-07-18",
    "Day":"Saturday.",
    "Order ID":"AB823",
    "Brand Name":"KAI The Sushi Bar, B Arcade Mall",
    "Delivery Distance":0.6,
    "Order Hour":18,
    "Prep Time":27,
    "Delivery Time":11,
    "E2E":38,
    "Delivery Channel":"Ando Fleet"
  },
  {
    "Order Date":"2026-07-18",
    "Day":"Saturday.",
    "Order ID":"2E8EF",
    "Brand Name":"KAI The Sushi Bar, B Arcade Mall",
    "Delivery Distance":3.5,
    "Order Hour":17,
    "Prep Time":17,
    "Delivery Time":14,
    "E2E":31,
    "Delivery Channel":"Ando Fleet"
  },
  {
    "Order Date":"2026-07-18",
    "Day":"Saturday.",
    "Order ID":"D3162.",
    "Brand Name":"KAI The Sushi Bar, B Arcade Mall",
    "Delivery Distance":8.6,
    "Order Hour":16,
    "Prep Time":19,
    "Delivery Time":27,
    "E2E":46,
    "Delivery Channel":"Ando Fleet"
  },
  {
    "Order Date":"2026-07-18",
    "Day":"Saturday.",
    "Order ID":"D6012",
    "Brand Name":"KAI The Sushi Bar, B Arcade Mall",
    "Delivery Distance":10.2,
    "Order Hour":16,
    "Prep Time":13,
    "Delivery Time":22,
    "E2E":35,
    "Delivery Channel":"Ando Fleet"
  },
  {
    "Order Date":"2026-07-18",
    "Day":"Saturday.",
    "Order ID":"02766",
    "Brand Name":"KAI The Sushi Bar, B Arcade Mall",
    "Delivery Distance":2.1,
    "Order Hour":16,
    "Prep Time":17,
    "Delivery Time":12,
    "E2E":29,
    "Delivery Channel":"Ando Fleet"
  },
  {
    "Order Date":"2026-07-18",
    "Day":"Saturday.",
    "Order ID":"CE017",
    "Brand Name":"KAI The Sushi Bar, Mpaka Rd",
    "Delivery Distance":2.5,
    "Order Hour":19,
    "Prep Time":4,
    "Delivery Time":15,
    "E2E":19,
    "Delivery Channel":"Ando Fleet"
  },
  {
    "Order Date":"2026-07-18",
    "Day":"Saturday.",
    "Order ID":"DA174",
    "Brand Name":"KAI The Sushi Bar, Mpaka Rd",
    "Delivery Distance":2.5,
    "Order Hour":19,
    "Prep Time":2,
    "Delivery Time":13,
    "E2E":15,
    "Delivery Channel":"Ando Fleet"
  },
  {
    "Order Date":"2026-07-18",
    "Day":"Saturday.",
    "Order ID":"69305",
    "Brand Name":"KAI The Sushi Bar, Mpaka Rd",
    "Delivery Distance":3.2,
    "Order Hour":15,
    "Prep Time":6,
    "Delivery Time":10,
    "E2E":16,
    "Delivery Channel":"Ando Fleet"
  },
  {
    "Order Date":"2026-07-18",
    "Day":"Saturday.",
    "Order ID":"101716759303",
    "Brand Name":"KAI The Sushi Bar, Mpaka Rd",
    "Delivery Distance":10.2,
    "Order Hour":14,
    "Prep Time":4,
    "Delivery Time":28,
    "E2E":32,
    "Delivery Channel":"Ando Fleet"
  },
  {
    "Order Date":"2026-07-18",
    "Day":"Saturday.",
    "Order ID":"91821",
    "Brand Name":"KAI The Sushi Bar, Mpaka Rd",
    "Delivery Distance":3.3,
    "Order Hour":13,
    "Prep Time":9,
    "Delivery Time":15,
    "E2E":24,
    "Delivery Channel":"Ando Fleet"
  },
  {
    "Order Date":"2026-07-18",
    "Day":"Saturday.",
    "Order ID":"E038A",
    "Brand Name":"KAI The Sushi Bar, Village Mkt",
    "Delivery Distance":3.6,
    "Order Hour":14,
    "Prep Time":31,
    "Delivery Time":21,
    "E2E":52,
    "Delivery Channel":"Uber Direct"
  },
  {
    "Order Date":"2026-07-18",
    "Day":"Saturday.",
    "Order ID":"101717096341",
    "Brand Name":"KAI The Sushi Bar, Village Mkt",
    "Delivery Distance":8.7,
    "Order Hour":18,
    "Prep Time":24,
    "Delivery Time":28,
    "E2E":52,
    "Delivery Channel":"Ando Fleet"
  },
  {
    "Order Date":"2026-07-18",
    "Day":"Saturday.",
    "Order ID":"101717070703",
    "Brand Name":"KAI The Sushi Bar, Village Mkt",
    "Delivery Distance":11.2,
    "Order Hour":18,
    "Prep Time":107,
    "Delivery Time":1,
    "E2E":108,
    "Delivery Channel":"Ando Fleet"
  },
  {
    "Order Date":"2026-07-18",
    "Day":"Saturday.",
    "Order ID":"101716782673",
    "Brand Name":"KAI The Sushi Bar, Village Mkt",
    "Delivery Distance":11.4,
    "Order Hour":13,
    "Prep Time":22,
    "Delivery Time":41,
    "E2E":63,
    "Delivery Channel":"Ando Fleet"
  },
  {
    "Order Date":"2026-07-18",
    "Day":"Saturday.",
    "Order ID":"7D9DD",
    "Brand Name":"Lagos Suya Spot, Nigerian Restaurant",
    "Delivery Distance":2.3,
    "Order Hour":18,
    "Prep Time":15,
    "Delivery Time":31,
    "E2E":46,
    "Delivery Channel":"Ando Fleet"
  },
  {
    "Order Date":"2026-07-18",
    "Day":"Saturday.",
    "Order ID":"16C49",
    "Brand Name":"Lagos Suya Spot, Nigerian Restaurant",
    "Delivery Distance":1.9,
    "Order Hour":17,
    "Prep Time":11,
    "Delivery Time":31,
    "E2E":42,
    "Delivery Channel":"Ando Fleet"
  },
  {
    "Order Date":"2026-07-18",
    "Day":"Saturday.",
    "Order ID":"63F86",
    "Brand Name":"Lagos Suya Spot, Nigerian Restaurant",
    "Delivery Distance":1.3,
    "Order Hour":17,
    "Prep Time":15,
    "Delivery Time":1,
    "E2E":16,
    "Delivery Channel":"Ando Fleet"
  },
  {
    "Order Date":"2026-07-18",
    "Day":"Saturday.",
    "Order ID":"1992F.",
    "Brand Name":"Lagos Suya Spot, Nigerian Restaurant",
    "Delivery Distance":5.5,
    "Order Hour":17,
    "Prep Time":16,
    "Delivery Time":33,
    "E2E":49,
    "Delivery Channel":"Ando Fleet"
  },
  {
    "Order Date":"2026-07-18",
    "Day":"Saturday.",
    "Order ID":"CD4B0",
    "Brand Name":"Lagos Suya Spot, Nigerian Restaurant",
    "Delivery Distance":1.5,
    "Order Hour":15,
    "Prep Time":16,
    "Delivery Time":26,
    "E2E":42,
    "Delivery Channel":"Ando Fleet"
  },
  {
    "Order Date":"2026-07-18",
    "Day":"Saturday.",
    "Order ID":"A85C4",
    "Brand Name":"Lagos Suya Spot, Nigerian Restaurant",
    "Delivery Distance":5.5,
    "Order Hour":15,
    "Prep Time":12,
    "Delivery Time":54,
    "E2E":66,
    "Delivery Channel":"Ando Fleet"
  },
  {
    "Order Date":"2026-07-18",
    "Day":"Saturday.",
    "Order ID":"68A24",
    "Brand Name":"Lagos Suya Spot, Nigerian Restaurant",
    "Delivery Distance":13.4,
    "Order Hour":13,
    "Prep Time":11,
    "Delivery Time":63,
    "E2E":74,
    "Delivery Channel":"Ando Fleet"
  },
  {
    "Order Date":"2026-07-18",
    "Day":"Saturday.",
    "Order ID":"227704",
    "Brand Name":"Lagos Suya Spot, Nigerian Restaurant",
    "Delivery Distance":8.1,
    "Order Hour":19,
    "Prep Time":18,
    "Delivery Time":14,
    "E2E":32,
    "Delivery Channel":"Uber Direct"
  },
  {
    "Order Date":"2026-07-18",
    "Day":"Saturday.",
    "Order ID":"41207",
    "Brand Name":"Li\u2019s Barbecue, Mombasa",
    "Delivery Distance":2.8,
    "Order Hour":15,
    "Prep Time":32,
    "Delivery Time":15,
    "E2E":47,
    "Delivery Channel":"Uber Direct"
  },
  {
    "Order Date":"2026-07-18",
    "Day":"Saturday.",
    "Order ID":"4B16C",
    "Brand Name":"Majani Grill",
    "Delivery Distance":8.5,
    "Order Hour":18,
    "Prep Time":56,
    "Delivery Time":24,
    "E2E":80,
    "Delivery Channel":"Uber Direct"
  },
  {
    "Order Date":"2026-07-18",
    "Day":"Saturday.",
    "Order ID":"12F64",
    "Brand Name":"Matam Barbacue and Drinks",
    "Delivery Distance":9.5,
    "Order Hour":18,
    "Prep Time":69,
    "Delivery Time":35,
    "E2E":104,
    "Delivery Channel":"Uber Direct"
  },
  {
    "Order Date":"2026-07-18",
    "Day":"Saturday.",
    "Order ID":"AE4BC",
    "Brand Name":"Matam Barbacue and Drinks",
    "Delivery Distance":3.9,
    "Order Hour":17,
    "Prep Time":69,
    "Delivery Time":27,
    "E2E":96,
    "Delivery Channel":"Uber Direct"
  },
  {
    "Order Date":"2026-07-18",
    "Day":"Saturday.",
    "Order ID":"9B7FB",
    "Brand Name":"Matam Barbacue and Drinks",
    "Delivery Distance":2.0,
    "Order Hour":14,
    "Prep Time":70,
    "Delivery Time":10,
    "E2E":80,
    "Delivery Channel":"Uber Direct"
  },
  {
    "Order Date":"2026-07-18",
    "Day":"Saturday.",
    "Order ID":"23B4C",
    "Brand Name":"Mix Grill n Doner",
    "Delivery Distance":3.8,
    "Order Hour":21,
    "Prep Time":22,
    "Delivery Time":16,
    "E2E":38,
    "Delivery Channel":"Uber Direct"
  },
  {
    "Order Date":"2026-07-18",
    "Day":"Saturday.",
    "Order ID":"E7195",
    "Brand Name":"Mix Grill n Doner",
    "Delivery Distance":11.8,
    "Order Hour":19,
    "Prep Time":52,
    "Delivery Time":27,
    "E2E":79,
    "Delivery Channel":"Uber Direct"
  },
  {
    "Order Date":"2026-07-18",
    "Day":"Saturday.",
    "Order ID":"AB2D5",
    "Brand Name":"Mix Grill n Doner",
    "Delivery Distance":9.8,
    "Order Hour":19,
    "Prep Time":36,
    "Delivery Time":16,
    "E2E":52,
    "Delivery Channel":"Uber Direct"
  },
  {
    "Order Date":"2026-07-18",
    "Day":"Saturday.",
    "Order ID":"806C1",
    "Brand Name":"Mix Grill n Doner",
    "Delivery Distance":5.9,
    "Order Hour":18,
    "Prep Time":17,
    "Delivery Time":16,
    "E2E":33,
    "Delivery Channel":"Uber Direct"
  },
  {
    "Order Date":"2026-07-18",
    "Day":"Saturday.",
    "Order ID":"FDC0E",
    "Brand Name":"Mix Grill n Doner",
    "Delivery Distance":16.8,
    "Order Hour":12,
    "Prep Time":47,
    "Delivery Time":51,
    "E2E":98,
    "Delivery Channel":"Uber Direct"
  },
  {
    "Order Date":"2026-07-18",
    "Day":"Saturday.",
    "Order ID":"CBD18",
    "Brand Name":"Mix Grill n Doner",
    "Delivery Distance":3.1,
    "Order Hour":13,
    "Prep Time":14,
    "Delivery Time":10,
    "E2E":24,
    "Delivery Channel":"Uber Direct"
  },
  {
    "Order Date":"2026-07-18",
    "Day":"Saturday.",
    "Order ID":"1890C",
    "Brand Name":"Mix Grill n Doner",
    "Delivery Distance":2.2,
    "Order Hour":12,
    "Prep Time":22,
    "Delivery Time":24,
    "E2E":46,
    "Delivery Channel":"Uber Direct"
  },
  {
    "Order Date":"2026-07-18",
    "Day":"Saturday.",
    "Order ID":"17189",
    "Brand Name":"New Mombasa Dishes",
    "Delivery Distance":9.4,
    "Order Hour":18,
    "Prep Time":70,
    "Delivery Time":24,
    "E2E":94,
    "Delivery Channel":"Uber Direct"
  },
  {
    "Order Date":"2026-07-18",
    "Day":"Saturday.",
    "Order ID":"02EF1",
    "Brand Name":"New Mombasa Dishes",
    "Delivery Distance":1.9,
    "Order Hour":15,
    "Prep Time":32,
    "Delivery Time":19,
    "E2E":51,
    "Delivery Channel":"Uber Direct"
  },
  {
    "Order Date":"2026-07-18",
    "Day":"Saturday.",
    "Order ID":"7BDBC",
    "Brand Name":"New Mombasa Dishes",
    "Delivery Distance":3.9,
    "Order Hour":14,
    "Prep Time":20,
    "Delivery Time":17,
    "E2E":37,
    "Delivery Channel":"Uber Direct"
  },
  {
    "Order Date":"2026-07-18",
    "Day":"Saturday.",
    "Order ID":"7495C",
    "Brand Name":"Noi Dumplings",
    "Delivery Distance":10.6,
    "Order Hour":19,
    "Prep Time":22,
    "Delivery Time":23,
    "E2E":45,
    "Delivery Channel":"Uber Direct"
  },
  {
    "Order Date":"2026-07-18",
    "Day":"Saturday.",
    "Order ID":"47960",
    "Brand Name":"Noi Dumplings",
    "Delivery Distance":11.5,
    "Order Hour":18,
    "Prep Time":26,
    "Delivery Time":28,
    "E2E":54,
    "Delivery Channel":"Uber Direct"
  },
  {
    "Order Date":"2026-07-18",
    "Day":"Saturday.",
    "Order ID":"A67BB",
    "Brand Name":"Noi Dumplings",
    "Delivery Distance":13.7,
    "Order Hour":18,
    "Prep Time":31,
    "Delivery Time":35,
    "E2E":66,
    "Delivery Channel":"Uber Direct"
  },
  {
    "Order Date":"2026-07-18",
    "Day":"Saturday.",
    "Order ID":"7E3C5",
    "Brand Name":"Noi Dumplings",
    "Delivery Distance":5.3,
    "Order Hour":17,
    "Prep Time":35,
    "Delivery Time":16,
    "E2E":51,
    "Delivery Channel":"Uber Direct"
  },
  {
    "Order Date":"2026-07-18",
    "Day":"Saturday.",
    "Order ID":"AEC64",
    "Brand Name":"Noi Dumplings",
    "Delivery Distance":6.6,
    "Order Hour":15,
    "Prep Time":49,
    "Delivery Time":21,
    "E2E":70,
    "Delivery Channel":"Uber Direct"
  },
  {
    "Order Date":"2026-07-18",
    "Day":"Saturday.",
    "Order ID":"6EE0E",
    "Brand Name":"Noi Dumplings",
    "Delivery Distance":12.1,
    "Order Hour":14,
    "Prep Time":27,
    "Delivery Time":26,
    "E2E":53,
    "Delivery Channel":"Uber Direct"
  },
  {
    "Order Date":"2026-07-18",
    "Day":"Saturday.",
    "Order ID":"3771B",
    "Brand Name":"Noi Dumplings",
    "Delivery Distance":6.4,
    "Order Hour":13,
    "Prep Time":28,
    "Delivery Time":19,
    "E2E":47,
    "Delivery Channel":"Uber Direct"
  },
  {
    "Order Date":"2026-07-18",
    "Day":"Saturday.",
    "Order ID":"8153C",
    "Brand Name":"Open House Restaurant Gallant Mall",
    "Delivery Distance":7.4,
    "Order Hour":18,
    "Prep Time":17,
    "Delivery Time":18,
    "E2E":35,
    "Delivery Channel":"Uber Direct"
  },
  {
    "Order Date":"2026-07-18",
    "Day":"Saturday.",
    "Order ID":"6BFEE",
    "Brand Name":"Open House Restaurant Gallant Mall",
    "Delivery Distance":10.0,
    "Order Hour":17,
    "Prep Time":29,
    "Delivery Time":28,
    "E2E":57,
    "Delivery Channel":"Uber Direct"
  },
  {
    "Order Date":"2026-07-18",
    "Day":"Saturday.",
    "Order ID":"6BF85",
    "Brand Name":"Open House Restaurant Karen",
    "Delivery Distance":2.3,
    "Order Hour":19,
    "Prep Time":20,
    "Delivery Time":15,
    "E2E":35,
    "Delivery Channel":"Uber Direct"
  },
  {
    "Order Date":"2026-07-18",
    "Day":"Saturday.",
    "Order ID":"3CBF2",
    "Brand Name":"Open House Restaurant Karen",
    "Delivery Distance":3.0,
    "Order Hour":17,
    "Prep Time":35,
    "Delivery Time":15,
    "E2E":50,
    "Delivery Channel":"Uber Direct"
  },
  {
    "Order Date":"2026-07-18",
    "Day":"Saturday.",
    "Order ID":"162F3",
    "Brand Name":"Open House Restaurant Karen",
    "Delivery Distance":3.1,
    "Order Hour":12,
    "Prep Time":20,
    "Delivery Time":12,
    "E2E":32,
    "Delivery Channel":"Uber Direct"
  },
  {
    "Order Date":"2026-07-18",
    "Day":"Saturday.",
    "Order ID":"63A80",
    "Brand Name":"Pizza Corner, Since 1989",
    "Delivery Distance":2.4,
    "Order Hour":21,
    "Prep Time":35,
    "Delivery Time":10,
    "E2E":45,
    "Delivery Channel":"Uber Direct"
  },
  {
    "Order Date":"2026-07-18",
    "Day":"Saturday.",
    "Order ID":"101717236677",
    "Brand Name":"Pizza Corner, Since 1989",
    "Delivery Distance":4.5,
    "Order Hour":20,
    "Prep Time":33,
    "Delivery Time":24,
    "E2E":57,
    "Delivery Channel":"Uber Direct"
  },
  {
    "Order Date":"2026-07-18",
    "Day":"Saturday.",
    "Order ID":"F60D2",
    "Brand Name":"Pizza Corner, Since 1989",
    "Delivery Distance":6.6,
    "Order Hour":18,
    "Prep Time":32,
    "Delivery Time":20,
    "E2E":52,
    "Delivery Channel":"Uber Direct"
  },
  {
    "Order Date":"2026-07-18",
    "Day":"Saturday.",
    "Order ID":"101717095053",
    "Brand Name":"Pizza Corner, Since 1989",
    "Delivery Distance":7.1,
    "Order Hour":18,
    "Prep Time":41,
    "Delivery Time":20,
    "E2E":61,
    "Delivery Channel":"Uber Direct"
  },
  {
    "Order Date":"2026-07-18",
    "Day":"Saturday.",
    "Order ID":"101717076139",
    "Brand Name":"Pizza Corner, Since 1989",
    "Delivery Distance":10.8,
    "Order Hour":18,
    "Prep Time":38,
    "Delivery Time":33,
    "E2E":71,
    "Delivery Channel":"Uber Direct"
  },
  {
    "Order Date":"2026-07-18",
    "Day":"Saturday.",
    "Order ID":"1DAFE",
    "Brand Name":"Pizza Corner, Since 1989",
    "Delivery Distance":0.9,
    "Order Hour":14,
    "Prep Time":27,
    "Delivery Time":8,
    "E2E":35,
    "Delivery Channel":"Uber Direct"
  },
  {
    "Order Date":"2026-07-18",
    "Day":"Saturday.",
    "Order ID":"5BDA3",
    "Brand Name":"Pot of Jollof Kitchen",
    "Delivery Distance":0.09,
    "Order Hour":21,
    "Prep Time":44,
    "Delivery Time":7,
    "E2E":51,
    "Delivery Channel":"Uber Direct"
  },
  {
    "Order Date":"2026-07-18",
    "Day":"Saturday.",
    "Order ID":"BC49A",
    "Brand Name":"Pot of Jollof Kitchen",
    "Delivery Distance":6.3,
    "Order Hour":20,
    "Prep Time":43,
    "Delivery Time":23,
    "E2E":66,
    "Delivery Channel":"Uber Direct"
  },
  {
    "Order Date":"2026-07-18",
    "Day":"Saturday.",
    "Order ID":"5905D",
    "Brand Name":"Pot of Jollof Kitchen",
    "Delivery Distance":2.9,
    "Order Hour":18,
    "Prep Time":29,
    "Delivery Time":18,
    "E2E":47,
    "Delivery Channel":"Uber Direct"
  },
  {
    "Order Date":"2026-07-18",
    "Day":"Saturday.",
    "Order ID":"DBA3E",
    "Brand Name":"Pot of Jollof Kitchen",
    "Delivery Distance":2.9,
    "Order Hour":16,
    "Prep Time":31,
    "Delivery Time":13,
    "E2E":44,
    "Delivery Channel":"Uber Direct"
  },
  {
    "Order Date":"2026-07-18",
    "Day":"Saturday.",
    "Order ID":"084CE",
    "Brand Name":"Pot of Jollof Kitchen",
    "Delivery Distance":0.9,
    "Order Hour":11,
    "Prep Time":22,
    "Delivery Time":13,
    "E2E":35,
    "Delivery Channel":"Uber Direct"
  },
  {
    "Order Date":"2026-07-18",
    "Day":"Saturday.",
    "Order ID":"227478",
    "Brand Name":"Pot of Jollof Kitchen",
    "Delivery Distance":7.9,
    "Order Hour":17,
    "Prep Time":1,
    "Delivery Time":8,
    "E2E":9,
    "Delivery Channel":"Ando Fleet"
  },
  {
    "Order Date":"2026-07-18",
    "Day":"Saturday.",
    "Order ID":"B47AF",
    "Brand Name":"Red Ginger",
    "Delivery Distance":2.9,
    "Order Hour":20,
    "Prep Time":17,
    "Delivery Time":12,
    "E2E":29,
    "Delivery Channel":"Uber Direct"
  },
  {
    "Order Date":"2026-07-18",
    "Day":"Saturday.",
    "Order ID":"AF7A2",
    "Brand Name":"Red Ginger",
    "Delivery Distance":10.1,
    "Order Hour":19,
    "Prep Time":23,
    "Delivery Time":30,
    "E2E":53,
    "Delivery Channel":"Uber Direct"
  },
  {
    "Order Date":"2026-07-18",
    "Day":"Saturday.",
    "Order ID":"54984",
    "Brand Name":"Red Ginger",
    "Delivery Distance":1.1,
    "Order Hour":20,
    "Prep Time":22,
    "Delivery Time":8,
    "E2E":30,
    "Delivery Channel":"Uber Direct"
  },
  {
    "Order Date":"2026-07-18",
    "Day":"Saturday.",
    "Order ID":"2193D",
    "Brand Name":"Red Ginger",
    "Delivery Distance":5.6,
    "Order Hour":18,
    "Prep Time":18,
    "Delivery Time":17,
    "E2E":35,
    "Delivery Channel":"Uber Direct"
  },
  {
    "Order Date":"2026-07-18",
    "Day":"Saturday.",
    "Order ID":"05BF9",
    "Brand Name":"Red Ginger",
    "Delivery Distance":8.4,
    "Order Hour":17,
    "Prep Time":27,
    "Delivery Time":25,
    "E2E":52,
    "Delivery Channel":"Uber Direct"
  },
  {
    "Order Date":"2026-07-18",
    "Day":"Saturday.",
    "Order ID":"3A555",
    "Brand Name":"Red Ginger",
    "Delivery Distance":2.5,
    "Order Hour":17,
    "Prep Time":19,
    "Delivery Time":40,
    "E2E":59,
    "Delivery Channel":"Uber Direct"
  },
  {
    "Order Date":"2026-07-18",
    "Day":"Saturday.",
    "Order ID":"64037",
    "Brand Name":"Red Ginger",
    "Delivery Distance":7.7,
    "Order Hour":16,
    "Prep Time":43,
    "Delivery Time":26,
    "E2E":69,
    "Delivery Channel":"Uber Direct"
  },
  {
    "Order Date":"2026-07-18",
    "Day":"Saturday.",
    "Order ID":"B7416",
    "Brand Name":"Red Ginger",
    "Delivery Distance":6.8,
    "Order Hour":16,
    "Prep Time":35,
    "Delivery Time":21,
    "E2E":56,
    "Delivery Channel":"Uber Direct"
  },
  {
    "Order Date":"2026-07-18",
    "Day":"Saturday.",
    "Order ID":"CC1E8",
    "Brand Name":"Red Ginger",
    "Delivery Distance":10.2,
    "Order Hour":16,
    "Prep Time":25,
    "Delivery Time":28,
    "E2E":53,
    "Delivery Channel":"Uber Direct"
  },
  {
    "Order Date":"2026-07-18",
    "Day":"Saturday.",
    "Order ID":"E9878",
    "Brand Name":"Red Ginger",
    "Delivery Distance":2.9,
    "Order Hour":16,
    "Prep Time":19,
    "Delivery Time":11,
    "E2E":30,
    "Delivery Channel":"Uber Direct"
  },
  {
    "Order Date":"2026-07-18",
    "Day":"Saturday.",
    "Order ID":"CBAA9",
    "Brand Name":"Red Ginger",
    "Delivery Distance":7.5,
    "Order Hour":14,
    "Prep Time":20,
    "Delivery Time":19,
    "E2E":39,
    "Delivery Channel":"Uber Direct"
  },
  {
    "Order Date":"2026-07-18",
    "Day":"Saturday.",
    "Order ID":"0AA2E",
    "Brand Name":"Red Ginger",
    "Delivery Distance":9.5,
    "Order Hour":13,
    "Prep Time":67,
    "Delivery Time":19,
    "E2E":86,
    "Delivery Channel":"Uber Direct"
  },
  {
    "Order Date":"2026-07-18",
    "Day":"Saturday.",
    "Order ID":"38F5F",
    "Brand Name":"Red Ginger",
    "Delivery Distance":7.7,
    "Order Hour":13,
    "Prep Time":30,
    "Delivery Time":28,
    "E2E":58,
    "Delivery Channel":"Uber Direct"
  },
  {
    "Order Date":"2026-07-18",
    "Day":"Saturday.",
    "Order ID":"16F02",
    "Brand Name":"Red Ginger",
    "Delivery Distance":3.9,
    "Order Hour":13,
    "Prep Time":27,
    "Delivery Time":21,
    "E2E":48,
    "Delivery Channel":"Uber Direct"
  },
  {
    "Order Date":"2026-07-18",
    "Day":"Saturday.",
    "Order ID":"5DA6D",
    "Brand Name":"Red Ginger",
    "Delivery Distance":5.4,
    "Order Hour":13,
    "Prep Time":33,
    "Delivery Time":24,
    "E2E":57,
    "Delivery Channel":"Uber Direct"
  },
  {
    "Order Date":"2026-07-18",
    "Day":"Saturday.",
    "Order ID":"84715",
    "Brand Name":"Red Ginger",
    "Delivery Distance":9.0,
    "Order Hour":13,
    "Prep Time":32,
    "Delivery Time":23,
    "E2E":55,
    "Delivery Channel":"Uber Direct"
  },
  {
    "Order Date":"2026-07-18",
    "Day":"Saturday.",
    "Order ID":"3131E",
    "Brand Name":"Red Ginger",
    "Delivery Distance":2.5,
    "Order Hour":13,
    "Prep Time":44,
    "Delivery Time":18,
    "E2E":62,
    "Delivery Channel":"Uber Direct"
  },
  {
    "Order Date":"2026-07-18",
    "Day":"Saturday.",
    "Order ID":"A15D9",
    "Brand Name":"Rozina's Gigiri",
    "Delivery Distance":6.2,
    "Order Hour":20,
    "Prep Time":22,
    "Delivery Time":25,
    "E2E":47,
    "Delivery Channel":"Uber Direct"
  },
  {
    "Order Date":"2026-07-18",
    "Day":"Saturday.",
    "Order ID":"5DE5A",
    "Brand Name":"Rozina's Westlands",
    "Delivery Distance":2.8,
    "Order Hour":18,
    "Prep Time":31,
    "Delivery Time":21,
    "E2E":52,
    "Delivery Channel":"Uber Direct"
  },
  {
    "Order Date":"2026-07-18",
    "Day":"Saturday.",
    "Order ID":"B0E41",
    "Brand Name":"Rozina's Westlands",
    "Delivery Distance":5.0,
    "Order Hour":17,
    "Prep Time":49,
    "Delivery Time":17,
    "E2E":66,
    "Delivery Channel":"Uber Direct"
  },
  {
    "Order Date":"2026-07-18",
    "Day":"Saturday.",
    "Order ID":"AB37D",
    "Brand Name":"Southern Vibes",
    "Delivery Distance":1.5,
    "Order Hour":20,
    "Prep Time":31,
    "Delivery Time":34,
    "E2E":65,
    "Delivery Channel":"Uber Direct"
  },
  {
    "Order Date":"2026-07-18",
    "Day":"Saturday.",
    "Order ID":"048B0",
    "Brand Name":"Southern Vibes",
    "Delivery Distance":9.7,
    "Order Hour":18,
    "Prep Time":29,
    "Delivery Time":30,
    "E2E":59,
    "Delivery Channel":"Uber Direct"
  },
  {
    "Order Date":"2026-07-18",
    "Day":"Saturday.",
    "Order ID":"860C5",
    "Brand Name":"Southern Vibes",
    "Delivery Distance":7.5,
    "Order Hour":14,
    "Prep Time":21,
    "Delivery Time":29,
    "E2E":50,
    "Delivery Channel":"Uber Direct"
  },
  {
    "Order Date":"2026-07-18",
    "Day":"Saturday.",
    "Order ID":"99EF6",
    "Brand Name":"Southern Vibes",
    "Delivery Distance":1.0,
    "Order Hour":14,
    "Prep Time":15,
    "Delivery Time":6,
    "E2E":21,
    "Delivery Channel":"Uber Direct"
  },
  {
    "Order Date":"2026-07-18",
    "Day":"Saturday.",
    "Order ID":"882FE",
    "Brand Name":"Southern Vibes",
    "Delivery Distance":7.3,
    "Order Hour":10,
    "Prep Time":35,
    "Delivery Time":38,
    "E2E":73,
    "Delivery Channel":"Uber Direct"
  },
  {
    "Order Date":"2026-07-18",
    "Day":"Saturday.",
    "Order ID":"25CC6",
    "Brand Name":"Sub Hub Restaurant",
    "Delivery Distance":5.1,
    "Order Hour":19,
    "Prep Time":29,
    "Delivery Time":16,
    "E2E":45,
    "Delivery Channel":"Uber Direct"
  },
  {
    "Order Date":"2026-07-18",
    "Day":"Saturday.",
    "Order ID":"226688",
    "Brand Name":"SUBZ (Timau Plaza)",
    "Delivery Distance":8.4,
    "Order Hour":13,
    "Prep Time":45,
    "Delivery Time":25,
    "E2E":70,
    "Delivery Channel":"Uber Direct"
  },
  {
    "Order Date":"2026-07-18",
    "Day":"Saturday.",
    "Order ID":"A0D5F",
    "Brand Name":"Supercuts Meat & Butchery",
    "Delivery Distance":1.3,
    "Order Hour":17,
    "Prep Time":10,
    "Delivery Time":8,
    "E2E":18,
    "Delivery Channel":"Uber Direct"
  },
  {
    "Order Date":"2026-07-18",
    "Day":"Saturday.",
    "Order ID":"227049",
    "Brand Name":"Supercuts Meat & Butchery",
    "Delivery Distance":4.2,
    "Order Hour":9,
    "Prep Time":24,
    "Delivery Time":15,
    "E2E":39,
    "Delivery Channel":"Uber Direct"
  },
  {
    "Order Date":"2026-07-18",
    "Day":"Saturday.",
    "Order ID":"4F4FB",
    "Brand Name":"Tamu Tamu Dishes",
    "Delivery Distance":11.8,
    "Order Hour":18,
    "Prep Time":14,
    "Delivery Time":37,
    "E2E":51,
    "Delivery Channel":"Uber Direct"
  },
  {
    "Order Date":"2026-07-18",
    "Day":"Saturday.",
    "Order ID":"DC7EF",
    "Brand Name":"Tamu Tamu Dishes",
    "Delivery Distance":0.02,
    "Order Hour":13,
    "Prep Time":16,
    "Delivery Time":5,
    "E2E":21,
    "Delivery Channel":"Uber Direct"
  },
  {
    "Order Date":"2026-07-18",
    "Day":"Saturday.",
    "Order ID":"A68E6",
    "Brand Name":"Tamu Tamu Dishes",
    "Delivery Distance":5.5,
    "Order Hour":11,
    "Prep Time":17,
    "Delivery Time":19,
    "E2E":36,
    "Delivery Channel":"Uber Direct"
  },
  {
    "Order Date":"2026-07-18",
    "Day":"Saturday.",
    "Order ID":"A6B00",
    "Brand Name":"Tandoori Patio",
    "Delivery Distance":7.2,
    "Order Hour":18,
    "Prep Time":49,
    "Delivery Time":23,
    "E2E":72,
    "Delivery Channel":"Uber Direct"
  },
  {
    "Order Date":"2026-07-18",
    "Day":"Saturday.",
    "Order ID":"D554C",
    "Brand Name":"Tandoori Patio",
    "Delivery Distance":11.5,
    "Order Hour":15,
    "Prep Time":21,
    "Delivery Time":29,
    "E2E":50,
    "Delivery Channel":"Uber Direct"
  },
  {
    "Order Date":"2026-07-18",
    "Day":"Saturday.",
    "Order ID":"18B07",
    "Brand Name":"Tandoori Patio",
    "Delivery Distance":7.8,
    "Order Hour":15,
    "Prep Time":42,
    "Delivery Time":24,
    "E2E":66,
    "Delivery Channel":"Uber Direct"
  },
  {
    "Order Date":"2026-07-18",
    "Day":"Saturday.",
    "Order ID":"2DCD1",
    "Brand Name":"Tandoori Patio",
    "Delivery Distance":9.4,
    "Order Hour":14,
    "Prep Time":15,
    "Delivery Time":61,
    "E2E":76,
    "Delivery Channel":"Uber Direct"
  },
  {
    "Order Date":"2026-07-18",
    "Day":"Saturday.",
    "Order ID":"45FBE",
    "Brand Name":"TastiGo",
    "Delivery Distance":1.3,
    "Order Hour":17,
    "Prep Time":25,
    "Delivery Time":7,
    "E2E":32,
    "Delivery Channel":"Uber Direct"
  },
  {
    "Order Date":"2026-07-18",
    "Day":"Saturday.",
    "Order ID":"BF2A3.",
    "Brand Name":"TastiWok",
    "Delivery Distance":6.2,
    "Order Hour":20,
    "Prep Time":21,
    "Delivery Time":4,
    "E2E":25,
    "Delivery Channel":"Ando Fleet"
  },
  {
    "Order Date":"2026-07-18",
    "Day":"Saturday.",
    "Order ID":"416EB",
    "Brand Name":"Wok This Way, Westlands",
    "Delivery Distance":2.7,
    "Order Hour":15,
    "Prep Time":60,
    "Delivery Time":15,
    "E2E":75,
    "Delivery Channel":"Uber Direct"
  },
  {
    "Order Date":"2026-07-18",
    "Day":"Saturday.",
    "Order ID":"227494",
    "Brand Name":"Wok This Way, Westlands",
    "Delivery Distance":4.7,
    "Order Hour":13,
    "Prep Time":45,
    "Delivery Time":14,
    "E2E":59,
    "Delivery Channel":"Uber Direct"
  },
  {
    "Order Date":"2026-07-18",
    "Day":"Saturday.",
    "Order ID":"5F582",
    "Brand Name":"Zarda Cafe",
    "Delivery Distance":2.5,
    "Order Hour":10,
    "Prep Time":41,
    "Delivery Time":10,
    "E2E":51,
    "Delivery Channel":"Uber Direct"
  },
  {
    "Order Date":"2026-07-18",
    "Day":"Saturday.",
    "Order ID":"18894",
    "Brand Name":"Zuri Pizza & Grilled Chicken",
    "Delivery Distance":5.9,
    "Order Hour":17,
    "Prep Time":19,
    "Delivery Time":35,
    "E2E":54,
    "Delivery Channel":"Uber Direct"
  },
  {
    "Order Date":"2026-07-18",
    "Day":"Saturday.",
    "Order ID":"43C98",
    "Brand Name":"Zuri Pizza & Grilled Chicken",
    "Delivery Distance":8.2,
    "Order Hour":11,
    "Prep Time":28,
    "Delivery Time":46,
    "E2E":74,
    "Delivery Channel":"Uber Direct"
  }
]